g42cloudsdkcdn/__init__.py
g42cloudsdkcdn/v1/__init__.py
g42cloudsdkcdn/v1/cdn_async_client.py
g42cloudsdkcdn/v1/cdn_client.py
g42cloudsdkcdn/v1/model/__init__.py
g42cloudsdkcdn/v1/model/black_white_list_body.py
g42cloudsdkcdn/v1/model/cache_config.py
g42cloudsdkcdn/v1/model/cache_config_request.py
g42cloudsdkcdn/v1/model/cache_config_request_body.py
g42cloudsdkcdn/v1/model/cdn_ips.py
g42cloudsdkcdn/v1/model/compress.py
g42cloudsdkcdn/v1/model/compress_request.py
g42cloudsdkcdn/v1/model/compress_response.py
g42cloudsdkcdn/v1/model/compress_rules.py
g42cloudsdkcdn/v1/model/configs.py
g42cloudsdkcdn/v1/model/configs_get_body.py
g42cloudsdkcdn/v1/model/create_domain_request.py
g42cloudsdkcdn/v1/model/create_domain_request_body.py
g42cloudsdkcdn/v1/model/create_domain_response.py
g42cloudsdkcdn/v1/model/create_domain_response_body_content.py
g42cloudsdkcdn/v1/model/create_preheating_tasks_request.py
g42cloudsdkcdn/v1/model/create_preheating_tasks_response.py
g42cloudsdkcdn/v1/model/create_refresh_tasks_request.py
g42cloudsdkcdn/v1/model/create_refresh_tasks_response.py
g42cloudsdkcdn/v1/model/delete_domain_request.py
g42cloudsdkcdn/v1/model/delete_domain_response.py
g42cloudsdkcdn/v1/model/disable_domain_request.py
g42cloudsdkcdn/v1/model/disable_domain_response.py
g42cloudsdkcdn/v1/model/domain_body.py
g42cloudsdkcdn/v1/model/domain_item_detail.py
g42cloudsdkcdn/v1/model/domain_item_location_details.py
g42cloudsdkcdn/v1/model/domain_origin_host.py
g42cloudsdkcdn/v1/model/domain_region.py
g42cloudsdkcdn/v1/model/domains.py
g42cloudsdkcdn/v1/model/domains_with_port.py
g42cloudsdkcdn/v1/model/enable_domain_request.py
g42cloudsdkcdn/v1/model/enable_domain_response.py
g42cloudsdkcdn/v1/model/follow302_status_body.py
g42cloudsdkcdn/v1/model/follow302_status_request.py
g42cloudsdkcdn/v1/model/force_redirect.py
g42cloudsdkcdn/v1/model/force_redirect_config.py
g42cloudsdkcdn/v1/model/header_body.py
g42cloudsdkcdn/v1/model/header_map.py
g42cloudsdkcdn/v1/model/http_get_body.py
g42cloudsdkcdn-0.0.10b0.dist-info/LICENSE
g42cloudsdkcdn-0.0.10b0.dist-info/METADATA
g42cloudsdkcdn-0.0.10b0.dist-info/WHEEL
g42cloudsdkcdn-0.0.10b0.dist-info/top_level.txt
g42cloudsdkcdn-0.0.10b0.dist-info/RECORD
